<bpy>
  <Theme>
    <user_interface>
      <ThemeUserInterface
        menu_shadow_fac="0.3"
        menu_shadow_width="4"
        icon_alpha="1"
        icon_saturation="0.5"
        widget_emboss="#1d202105"
        editor_outline="#1d2021"
        widget_text_cursor="#458588"
        panel_roundness="0.4"
        transparent_checker_primary="#3c3836"
        transparent_checker_secondary="#282828"
        transparent_checker_size="8"
        axis_x="#fb4934"
        axis_y="#b8bb26"
        axis_z="#458588"
        gizmo_hi="#fbf1c7"
        gizmo_primary="#fabd2f"
        gizmo_secondary="#83a598"
        gizmo_view_align="#1d2021"
        gizmo_a="#8ec07c"
        gizmo_b="#cc241d"
        icon_scene="#d5c4a1"
        icon_collection="#fbf1c7"
        icon_object="#fe8019"
        icon_object_data="#8ec07c"
        icon_modifier="#83a598"
        icon_shading="#d3869b"
        icon_folder="#D79921"
        icon_border_intensity="0"
        >
        <wcol_regular>
          <ThemeWidgetColors
            outline="#3c3836"
            inner="#504945ff"
            inner_sel="#d65d0ee6"
            item="#3c3836ff"
            text="#a89984"
            text_sel="#fbf1c7"
            show_shaded="FALSE"
            shadetop="0"
            shadedown="-5"
            roundness="0.4"
            >
          </ThemeWidgetColors>
        </wcol_regular>
        <wcol_tool>
          <ThemeWidgetColors
            outline="#3c3836"
            inner="#504945a0"
            inner_sel="#d65d0eff"
            item="#fbf1c7ff"
            text="#ebdbb2"
            text_sel="#fbf1c7"
            show_shaded="FALSE"
            shadetop="0"
            shadedown="-5"
            roundness="0.4"
            >
          </ThemeWidgetColors>
        </wcol_tool>
        <wcol_toolbar_item>
          <ThemeWidgetColors
            outline="#282828"
            inner="#32302fbf"
            inner_sel="#d65d0eff"
            item="#fbf1c78f"
            text="#ebdbb2"
            text_sel="#fbf1c7"
            show_shaded="FALSE"
            shadetop="0"
            shadedown="0"
            roundness="0.4"
            >
          </ThemeWidgetColors>
        </wcol_toolbar_item>
        <wcol_radio>
          <ThemeWidgetColors
            outline="#3c3836"
            inner="#504945ff"
            inner_sel="#d65d0ee6"
            item="#fbf1c7ff"
            text="#ebdbb2"
            text_sel="#fbf1c7"
            show_shaded="FALSE"
            shadetop="5"
            shadedown="-5"
            roundness="0.4"
            >
          </ThemeWidgetColors>
        </wcol_radio>
        <wcol_text>
          <ThemeWidgetColors
            outline="#3c3836"
            inner="#282828ff"
            inner_sel="#504945ff"
            item="#1d2021ff"
            text="#ebdbb2"
            text_sel="#fbf1c7"
            show_shaded="TRUE"
            shadetop="-3"
            shadedown="0"
            roundness="0.4"
            >
          </ThemeWidgetColors>
        </wcol_text>
        <wcol_option>
          <ThemeWidgetColors
            outline="#3c3836"
            inner="#665c54ff"
            inner_sel="#d65d0ee6"
            item="#fbf1c7ff"
            text="#ebdbb2"
            text_sel="#fbf1c7"
            show_shaded="FALSE"
            shadetop="0"
            shadedown="-15"
            roundness="0.4"
            >
          </ThemeWidgetColors>
        </wcol_option>
        <wcol_toggle>
          <ThemeWidgetColors
            outline="#3c3836"
            inner="#504945ff"
            inner_sel="#d65d0ee6"
            item="#1d2021ff"
            text="#ebdbb2"
            text_sel="#fbf1c7"
            show_shaded="FALSE"
            shadetop="0"
            shadedown="0"
            roundness="0.4"
            >
          </ThemeWidgetColors>
        </wcol_toggle>
        <wcol_num>
          <ThemeWidgetColors
            outline="#3c3836"
            inner="#504945ff"
            inner_sel="#665c54ff"
            item="#1d2021ff"
            text="#ebdbb2"
            text_sel="#fbf1c7"
            show_shaded="FALSE"
            shadetop="0"
            shadedown="0"
            roundness="0.4"
            >
          </ThemeWidgetColors>
        </wcol_num>
        <wcol_numslider>
          <ThemeWidgetColors
            outline="#3c3836"
            inner="#504945ff"
            inner_sel="#665c54ff"
            item="#d65d0ee6"
            text="#ebdbb2"
            text_sel="#fbf1c7"
            show_shaded="TRUE"
            shadetop="-4"
            shadedown="0"
            roundness="0.4"
            >
          </ThemeWidgetColors>
        </wcol_numslider>
        <wcol_box>
          <ThemeWidgetColors
            outline="#3c3836"
            inner="#1d202133"
            inner_sel="#665c54ff"
            item="#1d2021ff"
            text="#ebdbb2"
            text_sel="#fbf1c7"
            show_shaded="FALSE"
            shadetop="0"
            shadedown="0"
            roundness="0.4"
            >
          </ThemeWidgetColors>
        </wcol_box>
        <wcol_menu>
          <ThemeWidgetColors
            outline="#3c3836"
            inner="#282828ff"
            inner_sel="#665c54ff"
            item="#ebdbb2ff"
            text="#d5c4a1"
            text_sel="#fbf1c7"
            show_shaded="FALSE"
            shadetop="10"
            shadedown="-10"
            roundness="0.4"
            >
          </ThemeWidgetColors>
        </wcol_menu>
        <wcol_pulldown>
          <ThemeWidgetColors
            outline="#504945"
            inner="#282828cc"
            inner_sel="#504945e6"
            item="#fb4934ff"
            text="#d5c4a1"
            text_sel="#fbf1c7"
            show_shaded="FALSE"
            shadetop="25"
            shadedown="-20"
            roundness="0.4"
            >
          </ThemeWidgetColors>
        </wcol_pulldown>
        <wcol_menu_back>
          <ThemeWidgetColors
            outline="#282828"
            inner="#32302fe6"
            inner_sel="#504945ff"
            item="#fb4934ff"
            text="#a89984"
            text_sel="#fbf1c7"
            show_shaded="FALSE"
            shadetop="25"
            shadedown="-20"
            roundness="0.4"
            >
          </ThemeWidgetColors>
        </wcol_menu_back>
        <wcol_pie_menu>
          <ThemeWidgetColors
            outline="#282828"
            inner="#32302fff"
            inner_sel="#504945e6"
            item="#504945ff"
            text="#d5c4a1"
            text_sel="#fbf1c7"
            show_shaded="FALSE"
            shadetop="10"
            shadedown="-10"
            roundness="0.4"
            >
          </ThemeWidgetColors>
        </wcol_pie_menu>
        <wcol_tooltip>
          <ThemeWidgetColors
            outline="#282828"
            inner="#32302fef"
            inner_sel="#1d2021ef"
            item="#1d2021ef"
            text="#ebdbb2"
            text_sel="#fbf1c7"
            show_shaded="FALSE"
            shadetop="25"
            shadedown="-20"
            roundness="0.4"
            >
          </ThemeWidgetColors>
        </wcol_tooltip>
        <wcol_menu_item>
          <ThemeWidgetColors
            outline="#1d2021"
            inner="#1d202100"
            inner_sel="#504945e6"
            item="#fbf1c78f"
            text="#ebdbb2"
            text_sel="#fbf1c7"
            show_shaded="FALSE"
            shadetop="38"
            shadedown="0"
            roundness="0.4"
            >
          </ThemeWidgetColors>
        </wcol_menu_item>
        <wcol_scroll>
          <ThemeWidgetColors
            outline="#3c3836"
            inner="#665c5400"
            inner_sel="#bdae93ff"
            item="#665c54ff"
            text="#ebdbb2"
            text_sel="#fbf1c7"
            show_shaded="FALSE"
            shadetop="5"
            shadedown="-5"
            roundness="1"
            >
          </ThemeWidgetColors>
        </wcol_scroll>
        <wcol_progress>
          <ThemeWidgetColors
            outline="#504945"
            inner="#282828ff"
            inner_sel="#458588ff"
            item="#d65d0eff"
            text="#ebdbb2"
            text_sel="#fbf1c7"
            show_shaded="FALSE"
            shadetop="0"
            shadedown="0"
            roundness="0.4"
            >
          </ThemeWidgetColors>
        </wcol_progress>
        <wcol_list_item>
          <ThemeWidgetColors
            outline="#282828"
            inner="#28282800"
            inner_sel="#665c54ff"
            item="#bdae93ff"
            text="#ebdbb2"
            text_sel="#fbf1c7"
            show_shaded="FALSE"
            shadetop="0"
            shadedown="0"
            roundness="0.4"
            >
          </ThemeWidgetColors>
        </wcol_list_item>
        <wcol_state>
          <ThemeWidgetStateColors
            inner_anim="#b8bb26"
            inner_anim_sel="#98971a"
            inner_key="#fabd2f"
            inner_key_sel="#d79921"
            inner_driven="#b16286"
            inner_driven_sel="#8f3f71"
            inner_overridden="#83a598"
            inner_overridden_sel="#458588"
            inner_changed="#fe8019"
            inner_changed_sel="#d65d0e"
            blend="0.5"
            >
          </ThemeWidgetStateColors>
        </wcol_state>
        <wcol_tab>
          <ThemeWidgetColors
            outline="#282828"
            inner="#282828ff"
            inner_sel="#3c3836ff"
            item="#282828ff"
            text="#928374"
            text_sel="#fbf1c7"
            show_shaded="FALSE"
            shadetop="0"
            shadedown="0"
            roundness="0.4"
            >
          </ThemeWidgetColors>
        </wcol_tab>
      </ThemeUserInterface>
    </user_interface>
    <view_3d>
      <ThemeView3D
        grid="#d5c4a123"
        clipping_border_3d="#3c3836ff"
        wire="#1d2021"
        wire_edit="#a89984"
        edge_width="1"
        gp_vertex="#3c3836"
        gp_vertex_select="#fe8019"
        gp_vertex_size="4"
        text_grease_pencil="#b8bb26"
        object_selected="#d79921"
        object_active="#d65d0e"
        text_keyframe="#fabd2f"
        camera="#1d2021"
        empty="#1d2021"
        light="#1d202128"
        speaker="#1d2021"
        vertex="#1d2021"
        vertex_select="#fe8019"
        vertex_active="#fbf1c7ff"
        vertex_size="4"
        vertex_bevel="#458588"
        vertex_unreferenced="#1d2021"
        edge_select="#fe8019"
        edge_seam="#cc241d"
        edge_sharp="#83a598"
        edge_crease="#b16286"
        edge_bevel="#458588"
        edge_facesel="#504945"
        freestyle_edge_mark="#8ec07c"
        face="#fbf1c712"
        face_select="#fe80196c"
        face_dot="#d65d0e"
        facedot_size="4"
        freestyle_face_mark="#8ec07c4d"
        face_retopology="#83a5980f"
        face_back="#ff0000b3"
        face_front="#0000ffb3"
        nurb_uline="#98971a"
        nurb_vline="#b16286"
        nurb_sel_uline="#fabd2f"
        nurb_sel_vline="#d3869b"
        act_spline="#cc241d"
        handle_free="#1d2021"
        handle_auto="#98971a"
        handle_vect="#98971a"
        handle_sel_vect="#b8bb26"
        handle_align="#b16286"
        handle_sel_free="#1d2021"
        handle_sel_auto="#fabd2f"
        handle_sel_align="#d3869b"
        lastsel_point="#fbf1c7"
        extra_edge_len="#1d2021"
        extra_edge_angle="#98971a"
        extra_face_angle="#458588"
        extra_face_area="#689d6a"
        editmesh_active="#fbf1c7ff"
        normal="#83a598"
        vertex_normal="#458588"
        split_normal="#b16286"
        bone_pose="#83a598"
        bone_pose_active="#458588"
        bone_solid="#bdae93"
        bone_locked_weight="#cc241d80"
        bundle_solid="#d5c4a1"
        camera_path="#1d2021"
        camera_passepartout="#282828"
        skin_root="#cc241d"
        view_overlay="#1d2021"
        transform="#fbf1c7"
        frame_current="#8ec07c"
        paint_curve_handle="#8ec07c7f"
        paint_curve_pivot="#fb49347f"
        outline_width="5"
        object_origin_size="6"
        >
        <space>
          <ThemeSpaceGradient
            title="#ebdbb2"
            text="#ebdbb2"
            text_hi="#fbf1c7"
            header="#3c383600"
            header_text="#ebdbb2"
            header_text_hi="#fbf1c7"
            button="#3c383600"
            button_title="#fbf1c7"
            button_text="#ebdbb2"
            button_text_hi="#fbf1c7"
            navigation_bar="#1d202100"
            execution_buts="#1d202100"
            tab_active="#504945"
            tab_inactive="#282828"
            tab_back="#32302fff"
            tab_outline="#282828"
            >
            <gradients>
              <ThemeGradientColors
                background_type="SINGLE_COLOR"
                high_gradient="#3c3836"
                gradient="#3c3836"
                >
              </ThemeGradientColors>
            </gradients>
            <panelcolors>
              <ThemePanelColors
                header="#32302fe6"
                back="#3c3836f0"
                sub_back="#1d20213e"
                >
              </ThemePanelColors>
            </panelcolors>
          </ThemeSpaceGradient>
        </space>
        <asset_shelf>
          <ThemeAssetShelf
            header_back="#1d2021ff"
            back="#3c3836ff"
            >
          </ThemeAssetShelf>
        </asset_shelf>
      </ThemeView3D>
    </view_3d>
    <graph_editor>
      <ThemeGraphEditor
        grid="#504945"
        frame_current="#458588"
        time_scrub_background="#282828e6"
        time_marker_line="#1d202160"
        time_marker_line_selected="#fbf1c760"
        window_sliders="#928374"
        channels_region="#32302f"
        dopesheet_channel="#458588"
        dopesheet_subchannel="#83a598"
        channel_group="#79740e"
        active_channels_group="#98971a"
        preview_range="#d65d0e66"
        vertex="#1d2021"
        vertex_select="#fe8019"
        vertex_active="#fbf1c7"
        vertex_size="6"
        vertex_bevel="#1d2021"
        vertex_unreferenced="#1d2021"
        handle_free="#1d2021"
        handle_auto="#98971a"
        handle_vect="#98971a"
        handle_sel_vect="#b8bb26"
        handle_align="#b16286"
        handle_sel_free="#1d2021"
        handle_sel_auto="#fabd2f"
        handle_sel_align="#d3869b"
        handle_auto_clamped="#cc241d"
        handle_sel_auto_clamped="#fabd2f"
        lastsel_point="#fbf1c7"
        handle_vertex="#1d2021"
        handle_vertex_select="#fe8019"
        handle_vertex_size="5"
        >
        <space>
          <ThemeSpaceGeneric
            back="#3c3836"
            title="#fbf1c7"
            text="#ebdbb2"
            text_hi="#fbf1c7"
            header="#3c3836ff"
            header_text="#ebdbb2"
            header_text_hi="#fbf1c7"
            button="#3c3836ff"
            button_title="#fbf1c7"
            button_text="#ebdbb2"
            button_text_hi="#fbf1c7"
            navigation_bar="#1d202100"
            execution_buts="#1d202100"
            tab_active="#504945"
            tab_inactive="#282828"
            tab_back="#282828ff"
            tab_outline="#282828"
            >
            <panelcolors>
              <ThemePanelColors
                header="#28282880"
                back="#28282880"
                sub_back="#1d20211f"
                >
              </ThemePanelColors>
            </panelcolors>
          </ThemeSpaceGeneric>
        </space>
        <space_list>
          <ThemeSpaceListGeneric
            list="#3c3836"
            list_title="#fbf1c7"
            list_text="#fbf1c7"
            list_text_hi="#fabd2f"
            >
          </ThemeSpaceListGeneric>
        </space_list>
      </ThemeGraphEditor>
    </graph_editor>
    <file_browser>
      <ThemeFileBrowser
        selected_file="#d65d0e"
        row_alternate="#fbf1c707"
        >
        <space>
          <ThemeSpaceGeneric
            back="#3c3836"
            title="#fbf1c7"
            text="#ebdbb2"
            text_hi="#fbf1c7"
            header="#3c3836ff"
            header_text="#ebdbb2"
            header_text_hi="#fbf1c7"
            button="#3c3836ff"
            button_title="#fbf1c7"
            button_text="#ebdbb2"
            button_text_hi="#fbf1c7"
            navigation_bar="#1d202100"
            execution_buts="#1d202100"
            tab_active="#504945"
            tab_inactive="#282828"
            tab_back="#282828ff"
            tab_outline="#282828"
            >
            <panelcolors>
              <ThemePanelColors
                header="#28282880"
                back="#28282880"
                sub_back="#1d20211f"
                >
              </ThemePanelColors>
            </panelcolors>
          </ThemeSpaceGeneric>
        </space>
      </ThemeFileBrowser>
    </file_browser>
    <nla_editor>
      <ThemeNLAEditor
        grid="#504945"
        view_sliders="#928374"
        dopesheet_channel="#458588"
        dopesheet_subchannel="#7c6f64"
        nla_track="#3c3836"
        active_action="#d65d0e66"
        active_action_unset="#9283744d"
        preview_range="#d65d0e66"
        strips="#1d2021"
        strips_selected="#fe8019"
        transition_strips="#1d2021"
        transition_strips_selected="#458588"
        meta_strips="#b16286"
        meta_strips_selected="#d3869b"
        sound_strips="#282828"
        sound_strips_selected="#689d6a"
        tweak="#98971a"
        tweak_duplicate="#cc241d"
        keyframe_border="#1d2021ff"
        keyframe_border_selected="#1d2021ff"
        frame_current="#458588"
        time_scrub_background="#282828e6"
        time_marker_line="#1d202160"
        time_marker_line_selected="#fbf1c760"
        >
        <space>
          <ThemeSpaceGeneric
            back="#3c3836"
            title="#fbf1c7"
            text="#ebdbb2"
            text_hi="#fbf1c7"
            header="#3c3836ff"
            header_text="#ebdbb2"
            header_text_hi="#fbf1c7"
            button="#3c3836ff"
            button_title="#fbf1c7"
            button_text="#ebdbb2"
            button_text_hi="#fbf1c7"
            navigation_bar="#1d202100"
            execution_buts="#1d202100"
            tab_active="#504945"
            tab_inactive="#282828"
            tab_back="#282828ff"
            tab_outline="#282828"
            >
            <panelcolors>
              <ThemePanelColors
                header="#28282880"
                back="#28282880"
                sub_back="#1d20211f"
                >
              </ThemePanelColors>
            </panelcolors>
          </ThemeSpaceGeneric>
        </space>
        <space_list>
          <ThemeSpaceListGeneric
            list="#3c3836"
            list_title="#fbf1c7"
            list_text="#fbf1c7"
            list_text_hi="#fabd2f"
            >
          </ThemeSpaceListGeneric>
        </space_list>
      </ThemeNLAEditor>
    </nla_editor>
    <dopesheet_editor>
      <ThemeDopeSheet
        grid="#504945"
        frame_current="#458588"
        time_scrub_background="#282828e6"
        time_marker_line="#1d202160"
        time_marker_line_selected="#fbf1c760"
        value_sliders="#1d2021"
        view_sliders="#d5c4a1"
        dopesheet_channel="#45858824"
        dopesheet_subchannel="#83a59824"
        channels="#32302fff"
        channels_selected="#b8bb2644"
        channel_group="#79740e37"
        active_channels_group="#98971a55"
        long_key="#1d202180"
        long_key_selected="#fe8019cc"
        keyframe="#fbf1c7"
        keyframe_selected="#fabd2f"
        keyframe_extreme="#d3869b"
        keyframe_extreme_selected="#b16286"
        keyframe_breakdown="#83a598"
        keyframe_breakdown_selected="#458588"
        keyframe_jitter="#8ec07c"
        keyframe_jitter_selected="#689d6a"
        keyframe_movehold="#504945"
        keyframe_movehold_selected="#d79921"
        keyframe_border="#1d2021ff"
        keyframe_border_selected="#fbf1c7ff"
        keyframe_scale_factor="1"
        summary="#fe801966"
        preview_range="#d65d0e66"
        interpolation_line="#8ec07ccc"
        simulated_frames="#8f3f71ff"
        >
        <space>
          <ThemeSpaceGeneric
            back="#3c3836"
            title="#fbf1c7"
            text="#ebdbb2"
            text_hi="#fbf1c7"
            header="#3c3836ff"
            header_text="#ebdbb2"
            header_text_hi="#fbf1c7"
            button="#3c3836ff"
            button_title="#fbf1c7"
            button_text="#ebdbb2"
            button_text_hi="#fbf1c7"
            navigation_bar="#1d202100"
            execution_buts="#1d202100"
            tab_active="#504945"
            tab_inactive="#282828"
            tab_back="#282828ff"
            tab_outline="#282828"
            >
            <panelcolors>
              <ThemePanelColors
                header="#28282880"
                back="#28282880"
                sub_back="#1d20211f"
                >
              </ThemePanelColors>
            </panelcolors>
          </ThemeSpaceGeneric>
        </space>
        <space_list>
          <ThemeSpaceListGeneric
            list="#3c3836"
            list_title="#fbf1c7"
            list_text="#fbf1c7"
            list_text_hi="#fabd2f"
            >
          </ThemeSpaceListGeneric>
        </space_list>
      </ThemeDopeSheet>
    </dopesheet_editor>
    <image_editor>
      <ThemeImageEditor
        grid="#504945ff"
        vertex="#1d2021"
        vertex_select="#fe8019"
        vertex_active="#fbf1c780"
        vertex_size="3"
        vertex_bevel="#1d2021"
        vertex_unreferenced="#1d2021"
        face="#fbf1c70a"
        face_select="#fe80193c"
        face_dot="#fe8019"
        facedot_size="3"
        freestyle_face_mark="#8ec07c33"
        face_retopology="#282828"
        face_back="#1d202100"
        face_front="#1d202100"
        editmesh_active="#fbf1c780"
        wire_edit="#d5c4a1"
        edge_width="1"
        edge_select="#fe8019"
        scope_back="#504945ff"
        preview_stitch_face="#98971a33"
        preview_stitch_edge="#d3869b33"
        preview_stitch_vert="#45858833"
        preview_stitch_stitchable="#b8bb26ff"
        preview_stitch_unstitchable="#cc241dff"
        preview_stitch_active="#ebdbb223"
        uv_shadow="#a89984ff"
        frame_current="#8ec07c"
        metadatabg="#1d2021"
        metadatatext="#fbf1c7"
        handle_free="#1d2021"
        handle_auto="#98971a"
        handle_align="#b16286"
        handle_sel_free="#1d2021"
        handle_sel_auto="#d79921"
        handle_sel_align="#d3869b"
        handle_auto_clamped="#1d2021"
        handle_sel_auto_clamped="#1d2021"
        handle_vertex="#1d2021"
        handle_vertex_select="#fabd2f"
        handle_vertex_size="5"
        paint_curve_handle="#8ec07c7f"
        paint_curve_pivot="#fb49347f"
        >
        <space>
          <ThemeSpaceGeneric
            back="#3c3836"
            title="#fbf1c7"
            text="#ebdbb2"
            text_hi="#fbf1c7"
            header="#3c3836ff"
            header_text="#ebdbb2"
            header_text_hi="#fbf1c7"
            button="#3c383600"
            button_title="#fbf1c7"
            button_text="#ebdbb2"
            button_text_hi="#fbf1c7"
            navigation_bar="#1d202100"
            execution_buts="#1d202100"
            tab_active="#504945"
            tab_inactive="#282828"
            tab_back="#282828ff"
            tab_outline="#282828"
            >
            <panelcolors>
              <ThemePanelColors
                header="#32302fe6"
                back="#3c3836f0"
                sub_back="#1d20213e"
                >
              </ThemePanelColors>
            </panelcolors>
          </ThemeSpaceGeneric>
        </space>
      </ThemeImageEditor>
    </image_editor>
    <sequence_editor>
      <ThemeSequenceEditor
        grid="#504945"
        window_sliders="#a89984"
        movie_strip="#076678"
        movieclip_strip="#d65d0e"
        image_strip="#d79921"
        scene_strip="#98971a"
        audio_strip="#83a598"
        effect_strip="#b16286"
        transition_strip="#b16286"
        color_strip="#928374"
        meta_strip="#b16286"
        mask_strip="#665c54"
        text_strip="#8f3f71"
        active_strip="#d5c4a1"
        selected_strip="#fe8019"
        frame_current="#458588"
        time_scrub_background="#282828e6"
        time_marker_line="#1d202160"
        time_marker_line_selected="#fbf1c760"
        keyframe="#fe8019"
        keyframe_selected="#fbf1c7"
        keyframe_breakdown="#83a598"
        keyframe_breakdown_selected="#458588"
        keyframe_movehold="#7c6f64"
        keyframe_movehold_selected="#d79921"
        keyframe_border="#282828ff"
        keyframe_border_selected="#282828ff"
        draw_action="#83a598"
        preview_back="#1d2021"
        metadatabg="#1d2021"
        metadatatext="#fbf1c7"
        preview_range="#d65d0e66"
        row_alternate="#fbf1c70d"
        >
        <space>
          <ThemeSpaceGeneric
            back="#3c3836"
            title="#fbf1c7"
            text="#ebdbb2"
            text_hi="#fbf1c7"
            header="#3c3836ff"
            header_text="#ebdbb2"
            header_text_hi="#fbf1c7"
            button="#3c3836ff"
            button_title="#fbf1c7"
            button_text="#ebdbb2"
            button_text_hi="#fbf1c7"
            navigation_bar="#1d202100"
            execution_buts="#1d202100"
            tab_active="#504945"
            tab_inactive="#282828"
            tab_back="#282828ff"
            tab_outline="#282828"
            >
            <panelcolors>
              <ThemePanelColors
                header="#28282880"
                back="#28282880"
                sub_back="#1d20211f"
                >
              </ThemePanelColors>
            </panelcolors>
          </ThemeSpaceGeneric>
        </space>
        <space_list>
          <ThemeSpaceListGeneric
            list="#3c3836"
            list_title="#ebdbb2"
            list_text="#ebdbb2"
            list_text_hi="#fabd2f"
            >
          </ThemeSpaceListGeneric>
        </space_list>
      </ThemeSequenceEditor>
    </sequence_editor>
    <properties>
      <ThemeProperties
        match="#665c54"
        active_modifier="#504945ff"
        >
        <space>
          <ThemeSpaceGeneric
            back="#3c3836"
            title="#fbf1c7"
            text="#ebdbb2"
            text_hi="#fbf1c7"
            header="#3c3836ff"
            header_text="#ebdbb2"
            header_text_hi="#fbf1c7"
            button="#3c3836ff"
            button_title="#fbf1c7"
            button_text="#ebdbb2"
            button_text_hi="#fbf1c7"
            navigation_bar="#282828ff"
            execution_buts="#1d202100"
            tab_active="#504945"
            tab_inactive="#282828"
            tab_back="#282828ff"
            tab_outline="#282828"
            >
            <panelcolors>
              <ThemePanelColors
                header="#28282880"
                back="#28282880"
                sub_back="#1d20211f"
                >
              </ThemePanelColors>
            </panelcolors>
          </ThemeSpaceGeneric>
        </space>
      </ThemeProperties>
    </properties>
    <text_editor>
      <ThemeTextEditor
        line_numbers="#d5c4a1"
        line_numbers_background="#282828"
        selected_text="#83A598"
        cursor="#cc241d"
        syntax_builtin="#fb4934"
        syntax_symbols="#fe8019"
        syntax_special="#98971a"
        syntax_preprocessor="#b16286"
        syntax_reserved="#d65d0e"
        syntax_comment="#928374"
        syntax_string="#fabd2f"
        syntax_numbers="#458588"
        >
        <space>
          <ThemeSpaceGeneric
            back="#3c3836"
            title="#fbf1c7"
            text="#ebdbb2"
            text_hi="#fbf1c7"
            header="#3c3836ff"
            header_text="#ebdbb2"
            header_text_hi="#fbf1c7"
            button="#3c3836ff"
            button_title="#fbf1c7"
            button_text="#ebdbb2"
            button_text_hi="#fbf1c7"
            navigation_bar="#1d202100"
            execution_buts="#1d202100"
            tab_active="#504945"
            tab_inactive="#282828"
            tab_back="#282828ff"
            tab_outline="#282828"
            >
            <panelcolors>
              <ThemePanelColors
                header="#28282880"
                back="#28282880"
                sub_back="#1d20211f"
                >
              </ThemePanelColors>
            </panelcolors>
          </ThemeSpaceGeneric>
        </space>
      </ThemeTextEditor>
    </text_editor>
    <node_editor>
      <ThemeNodeEditor
        grid="#3c3836"
        node_selected="#d65d0e"
        node_active="#fbf1c7"
        wire="#928374"
        wire_inner="#928374"
        wire_select="#fbf1c7"
        selected_text="#7c6f64"
        node_backdrop="#504945ff"
        converter_node="#458588ff"
        color_node="#d79921"
        group_node="#98971ab9"
        group_socket_node="#1d2021"
        frame_node="#1d2021cc"
        matte_node="#b16286"
        distor_node="#83a598"
        noodle_curving="5"
        grid_levels="7"
        dash_alpha="0.5"
        input_node="#fb4934"
        output_node="#cc241d"
        filter_node="#b16286"
        vector_node="#d3869b"
        texture_node="#fe8019"
        shader_node="#8ec07c"
        script_node="#79740e"
        pattern_node="#665c54"
        layout_node="#665c54"
        geometry_node="#689d6a"
        attribute_node="#458588"
        simulation_zone="#8f3f7133"
        repeat_zone="#7c6f6433"
        >
        <space>
          <ThemeSpaceGeneric
            back="#282828"
            title="#fbf1c7"
            text="#ebdbb2"
            text_hi="#fbf1c7"
            header="#3c3836ff"
            header_text="#ebdbb2"
            header_text_hi="#fbf1c7"
            button="#3c3836ff"
            button_title="#fbf1c7"
            button_text="#ebdbb2"
            button_text_hi="#fbf1c7"
            navigation_bar="#1d202100"
            execution_buts="#1d202100"
            tab_active="#504945"
            tab_inactive="#282828"
            tab_back="#282828ff"
            tab_outline="#282828"
            >
            <panelcolors>
              <ThemePanelColors
                header="#28282880"
                back="#28282880"
                sub_back="#1d20211f"
                >
              </ThemePanelColors>
            </panelcolors>
          </ThemeSpaceGeneric>
        </space>
        <space_list>
          <ThemeSpaceListGeneric
            list="#3c3836"
            list_title="#fbf1c7"
            list_text="#fbf1c7"
            list_text_hi="#fabd2f"
            >
          </ThemeSpaceListGeneric>
        </space_list>
      </ThemeNodeEditor>
    </node_editor>
    <outliner>
      <ThemeOutliner
        match="#665c54"
        selected_highlight="#504945"
        active="#665c54"
        selected_object="#fabd2f"
        active_object="#fe8019"
        edited_object="#98971a66"
        row_alternate="#fbf1c707"
        >
        <space>
          <ThemeSpaceGeneric
            back="#3c3836"
            title="#fbf1c7"
            text="#ebdbb2"
            text_hi="#fbf1c7"
            header="#3c3836ff"
            header_text="#ebdbb2"
            header_text_hi="#fbf1c7"
            button="#3c3836ff"
            button_title="#fbf1c7"
            button_text="#ebdbb2"
            button_text_hi="#fbf1c7"
            navigation_bar="#1d202100"
            execution_buts="#1d202100"
            tab_active="#504945"
            tab_inactive="#282828"
            tab_back="#282828ff"
            tab_outline="#282828"
            >
            <panelcolors>
              <ThemePanelColors
                header="#28282880"
                back="#28282880"
                sub_back="#1d20211f"
                >
              </ThemePanelColors>
            </panelcolors>
          </ThemeSpaceGeneric>
        </space>
      </ThemeOutliner>
    </outliner>
    <info>
      <ThemeInfo
        info_selected="#d65d0e"
        info_selected_text="#fbf1c7"
        info_error="#cc241d"
        info_error_text="#fbf1c7"
        info_warning="#fb4934"
        info_warning_text="#fbf1c7"
        info_info="#458588"
        info_info_text="#fbf1c7"
        info_debug="#d5c4a1"
        info_debug_text="#1d2021"
        info_property="#689d6aff"
        info_property_text="#fbf1c7"
        info_operator="#689d6aff"
        info_operator_text="#fbf1c7"
        >
        <space>
          <ThemeSpaceGeneric
            back="#3c3836"
            title="#fbf1c7"
            text="#ebdbb2"
            text_hi="#fbf1c7"
            header="#3c3836ff"
            header_text="#ebdbb2"
            header_text_hi="#fbf1c7"
            button="#3c3836ff"
            button_title="#fbf1c7"
            button_text="#ebdbb2"
            button_text_hi="#fbf1c7"
            navigation_bar="#1d202100"
            execution_buts="#1d202100"
            tab_active="#504945"
            tab_inactive="#282828"
            tab_back="#282828ff"
            tab_outline="#282828"
            >
            <panelcolors>
              <ThemePanelColors
                header="#28282880"
                back="#28282880"
                sub_back="#1d20211f"
                >
              </ThemePanelColors>
            </panelcolors>
          </ThemeSpaceGeneric>
        </space>
      </ThemeInfo>
    </info>
    <preferences>
      <ThemePreferences>
        <space>
          <ThemeSpaceGeneric
            back="#3c3836"
            title="#fbf1c7"
            text="#ebdbb2"
            text_hi="#fbf1c7"
            header="#3c3836ff"
            header_text="#ebdbb2"
            header_text_hi="#fbf1c7"
            button="#3c3836ff"
            button_title="#fbf1c7"
            button_text="#ebdbb2"
            button_text_hi="#fbf1c7"
            navigation_bar="#3c3836ff"
            execution_buts="#3c3836ff"
            tab_active="#3c3836"
            tab_inactive="#282828"
            tab_back="#282828ff"
            tab_outline="#282828"
            >
            <panelcolors>
              <ThemePanelColors
                header="#28282880"
                back="#28282880"
                sub_back="#1d20211f"
                >
              </ThemePanelColors>
            </panelcolors>
          </ThemeSpaceGeneric>
        </space>
      </ThemePreferences>
    </preferences>
    <console>
      <ThemeConsole
        line_output="#83a598"
        line_input="#fbf1c7"
        line_info="#98971a"
        line_error="#d3869b"
        cursor="#cc241d"
        select="#fbf1c730"
        >
        <space>
          <ThemeSpaceGeneric
            back="#3c3836"
            title="#fbf1c7"
            text="#ebdbb2"
            text_hi="#fbf1c7"
            header="#3c3836ff"
            header_text="#ebdbb2"
            header_text_hi="#fbf1c7"
            button="#3c3836ff"
            button_title="#fbf1c7"
            button_text="#ebdbb2"
            button_text_hi="#fbf1c7"
            navigation_bar="#1d202100"
            execution_buts="#1d202100"
            tab_active="#504945"
            tab_inactive="#282828"
            tab_back="#282828ff"
            tab_outline="#282828"
            >
            <panelcolors>
              <ThemePanelColors
                header="#28282880"
                back="#28282880"
                sub_back="#1d20211f"
                >
              </ThemePanelColors>
            </panelcolors>
          </ThemeSpaceGeneric>
        </space>
      </ThemeConsole>
    </console>
    <clip_editor>
      <ThemeClipEditor
        grid="#504945"
        marker_outline="#1d2021"
        marker="#98971a"
        active_marker="#fbf1c7"
        selected_marker="#fabd2f"
        disabled_marker="#cc241d"
        locked_marker="#7c6f64"
        path_before="#cc241d"
        path_after="#458588"
        path_keyframe_before="#d3869b"
        path_keyframe_after="#83a598"
        frame_current="#458588"
        time_scrub_background="#282828e6"
        time_marker_line="#1d202160"
        time_marker_line_selected="#fbf1c760"
        strips="#1d2021"
        strips_selected="#fe8019"
        metadatabg="#1d2021"
        metadatatext="#fbf1c7"
        handle_free="#1d2021"
        handle_auto="#98971a"
        handle_align="#b16286"
        handle_sel_free="#1d2021"
        handle_sel_auto="#fabd2f"
        handle_sel_align="#d3869b"
        handle_auto_clamped="#1d2021"
        handle_sel_auto_clamped="#1d2021"
        handle_vertex="#1d2021"
        handle_vertex_select="#fabd2f"
        handle_vertex_size="5"
        >
        <space>
          <ThemeSpaceGeneric
            back="#3c3836"
            title="#fbf1c7"
            text="#ebdbb2"
            text_hi="#fbf1c7"
            header="#3c3836ff"
            header_text="#ebdbb2"
            header_text_hi="#fbf1c7"
            button="#3c3836ff"
            button_title="#fbf1c7"
            button_text="#ebdbb2"
            button_text_hi="#fbf1c7"
            navigation_bar="#1d202100"
            execution_buts="#1d202100"
            tab_active="#504945"
            tab_inactive="#282828"
            tab_back="#282828ff"
            tab_outline="#282828"
            >
            <panelcolors>
              <ThemePanelColors
                header="#32302fe6"
                back="#3c3836f0"
                sub_back="#1d20213e"
                >
              </ThemePanelColors>
            </panelcolors>
          </ThemeSpaceGeneric>
        </space>
        <space_list>
          <ThemeSpaceListGeneric
            list="#3c3836"
            list_title="#fbf1c7"
            list_text="#fbf1c7"
            list_text_hi="#fabd2f"
            >
          </ThemeSpaceListGeneric>
        </space_list>
      </ThemeClipEditor>
    </clip_editor>
    <topbar>
      <ThemeTopBar>
        <space>
          <ThemeSpaceGeneric
            back="#3c3836"
            title="#fbf1c7"
            text="#ebdbb2"
            text_hi="#fbf1c7"
            header="#32302fff"
            header_text="#ebdbb2"
            header_text_hi="#fbf1c7"
            button="#3c3836ff"
            button_title="#fbf1c7"
            button_text="#ebdbb2"
            button_text_hi="#fbf1c7"
            navigation_bar="#1d202100"
            execution_buts="#1d202100"
            tab_active="#504945"
            tab_inactive="#282828"
            tab_back="#282828ff"
            tab_outline="#282828"
            >
            <panelcolors>
              <ThemePanelColors
                header="#32302fe6"
                back="#3c3836f0"
                sub_back="#1d20213e"
                >
              </ThemePanelColors>
            </panelcolors>
          </ThemeSpaceGeneric>
        </space>
      </ThemeTopBar>
    </topbar>
    <statusbar>
      <ThemeStatusBar>
        <space>
          <ThemeSpaceGeneric
            back="#3c3836"
            title="#fbf1c7"
            text="#ebdbb2"
            text_hi="#fbf1c7"
            header="#32302fff"
            header_text="#ebdbb2"
            header_text_hi="#fbf1c7"
            button="#32302fff"
            button_title="#fbf1c7"
            button_text="#ebdbb2"
            button_text_hi="#fbf1c7"
            navigation_bar="#1d202100"
            execution_buts="#1d202100"
            tab_active="#504945"
            tab_inactive="#282828"
            tab_back="#282828ff"
            tab_outline="#282828"
            >
            <panelcolors>
              <ThemePanelColors
                header="#32302fe6"
                back="#3c3836f0"
                sub_back="#1d20213e"
                >
              </ThemePanelColors>
            </panelcolors>
          </ThemeSpaceGeneric>
        </space>
      </ThemeStatusBar>
    </statusbar>
    <spreadsheet>
      <ThemeSpreadsheet
        row_alternate="#fbf1c707"
        >
        <space>
          <ThemeSpaceGeneric
            back="#3c3836"
            title="#fbf1c7"
            text="#ebdbb2"
            text_hi="#fbf1c7"
            header="#3c3836ff"
            header_text="#ebdbb2"
            header_text_hi="#fbf1c7"
            button="#3c3836ff"
            button_title="#fbf1c7"
            button_text="#ebdbb2"
            button_text_hi="#fbf1c7"
            navigation_bar="#1d202100"
            execution_buts="#1d202100"
            tab_active="#504945"
            tab_inactive="#282828"
            tab_back="#282828ff"
            tab_outline="#282828"
            >
            <panelcolors>
              <ThemePanelColors
                header="#28282880"
                back="#28282880"
                sub_back="#1d20211f"
                >
              </ThemePanelColors>
            </panelcolors>
          </ThemeSpaceGeneric>
        </space>
        <space_list>
          <ThemeSpaceListGeneric
            list="#3c3836"
            list_title="#fbf1c7"
            list_text="#fbf1c7"
            list_text_hi="#fabd2f"
            >
          </ThemeSpaceListGeneric>
        </space_list>
      </ThemeSpreadsheet>
    </spreadsheet>
    <bone_color_sets>
      <ThemeBoneColorSet
        normal="#9a0000"
        select="#bd1111"
        active="#f70a0a"
        show_colored_constraints="FALSE"
        >
      </ThemeBoneColorSet>
      <ThemeBoneColorSet
        normal="#f74018"
        select="#f66913"
        active="#fa9900"
        show_colored_constraints="FALSE"
        >
      </ThemeBoneColorSet>
      <ThemeBoneColorSet
        normal="#1e9109"
        select="#59b70b"
        active="#83ef1d"
        show_colored_constraints="FALSE"
        >
      </ThemeBoneColorSet>
      <ThemeBoneColorSet
        normal="#0a3694"
        select="#3667df"
        active="#5ec1ef"
        show_colored_constraints="FALSE"
        >
      </ThemeBoneColorSet>
      <ThemeBoneColorSet
        normal="#a9294e"
        select="#c1416a"
        active="#f05d91"
        show_colored_constraints="FALSE"
        >
      </ThemeBoneColorSet>
      <ThemeBoneColorSet
        normal="#430c78"
        select="#543aa3"
        active="#8764d5"
        show_colored_constraints="FALSE"
        >
      </ThemeBoneColorSet>
      <ThemeBoneColorSet
        normal="#24785a"
        select="#3c9579"
        active="#6fb6ab"
        show_colored_constraints="FALSE"
        >
      </ThemeBoneColorSet>
      <ThemeBoneColorSet
        normal="#4b707c"
        select="#6a8691"
        active="#9bc2cd"
        show_colored_constraints="FALSE"
        >
      </ThemeBoneColorSet>
      <ThemeBoneColorSet
        normal="#f4c90c"
        select="#eec236"
        active="#f3ff00"
        show_colored_constraints="FALSE"
        >
      </ThemeBoneColorSet>
      <ThemeBoneColorSet
        normal="#1e2024"
        select="#484c56"
        active="#fbf1c7"
        show_colored_constraints="FALSE"
        >
      </ThemeBoneColorSet>
      <ThemeBoneColorSet
        normal="#6f2f6a"
        select="#9845be"
        active="#d330d6"
        show_colored_constraints="FALSE"
        >
      </ThemeBoneColorSet>
      <ThemeBoneColorSet
        normal="#6c8e22"
        select="#7fb022"
        active="#bbef5b"
        show_colored_constraints="FALSE"
        >
      </ThemeBoneColorSet>
      <ThemeBoneColorSet
        normal="#8d8d8d"
        select="#b0b0b0"
        active="#dedede"
        show_colored_constraints="FALSE"
        >
      </ThemeBoneColorSet>
      <ThemeBoneColorSet
        normal="#834326"
        select="#8b5811"
        active="#bd6a11"
        show_colored_constraints="FALSE"
        >
      </ThemeBoneColorSet>
      <ThemeBoneColorSet
        normal="#08310e"
        select="#1c430b"
        active="#34622b"
        show_colored_constraints="FALSE"
        >
      </ThemeBoneColorSet>
      <ThemeBoneColorSet
        normal="#1d2021"
        select="#1d2021"
        active="#1d2021"
        show_colored_constraints="FALSE"
        >
      </ThemeBoneColorSet>
      <ThemeBoneColorSet
        normal="#1d2021"
        select="#1d2021"
        active="#1d2021"
        show_colored_constraints="FALSE"
        >
      </ThemeBoneColorSet>
      <ThemeBoneColorSet
        normal="#1d2021"
        select="#1d2021"
        active="#1d2021"
        show_colored_constraints="FALSE"
        >
      </ThemeBoneColorSet>
      <ThemeBoneColorSet
        normal="#1d2021"
        select="#1d2021"
        active="#1d2021"
        show_colored_constraints="FALSE"
        >
      </ThemeBoneColorSet>
      <ThemeBoneColorSet
        normal="#1d2021"
        select="#1d2021"
        active="#1d2021"
        show_colored_constraints="FALSE"
        >
      </ThemeBoneColorSet>
    </bone_color_sets>
    <collection_color>
      <ThemeCollectionColor
        color="#fb4934"
        >
      </ThemeCollectionColor>
      <ThemeCollectionColor
        color="#fe8019"
        >
      </ThemeCollectionColor>
      <ThemeCollectionColor
        color="#fabd2f"
        >
      </ThemeCollectionColor>
      <ThemeCollectionColor
        color="#b8bb26"
        >
      </ThemeCollectionColor>
      <ThemeCollectionColor
        color="#83a598"
        >
      </ThemeCollectionColor>
      <ThemeCollectionColor
        color="#8f3f71"
        >
      </ThemeCollectionColor>
      <ThemeCollectionColor
        color="#d3869b"
        >
      </ThemeCollectionColor>
      <ThemeCollectionColor
        color="#B57614"
        >
      </ThemeCollectionColor>
    </collection_color>
    <strip_color>
      <ThemeStripColor
        color="#fb4934"
        >
      </ThemeStripColor>
      <ThemeStripColor
        color="#fe8019"
        >
      </ThemeStripColor>
      <ThemeStripColor
        color="#fabd2f"
        >
      </ThemeStripColor>
      <ThemeStripColor
        color="#b8bb26"
        >
      </ThemeStripColor>
      <ThemeStripColor
        color="#83a598"
        >
      </ThemeStripColor>
      <ThemeStripColor
        color="#8f3f71"
        >
      </ThemeStripColor>
      <ThemeStripColor
        color="#d3869b"
        >
      </ThemeStripColor>
      <ThemeStripColor
        color="#b57614"
        >
      </ThemeStripColor>
      <ThemeStripColor
        color="#665c54"
        >
      </ThemeStripColor>
    </strip_color>
  </Theme>
  <ThemeStyle>
    <panel_title>
      <ThemeFontStyle
        points="12"
        shadow="3"
        shadow_offset_x="0"
        shadow_offset_y="-1"
        shadow_alpha="0.5"
        shadow_value="0"
        >
      </ThemeFontStyle>
    </panel_title>
    <widget_label>
      <ThemeFontStyle
        points="11"
        shadow="3"
        shadow_offset_x="0"
        shadow_offset_y="-1"
        shadow_alpha="0.5"
        shadow_value="0"
        >
      </ThemeFontStyle>
    </widget_label>
    <widget>
      <ThemeFontStyle
        points="11"
        shadow="1"
        shadow_offset_x="0"
        shadow_offset_y="-1"
        shadow_alpha="0.5"
        shadow_value="0"
        >
      </ThemeFontStyle>
    </widget>
  </ThemeStyle>
</bpy>
